mcpconn/__init__.py
mcpconn/client.py
mcpconn/guardrails.py
mcpconn/transport.py
mcpconn/utils.py
mcpconn/llm/__init__.py
mcpconn/llm/anthropic.py
mcpconn/llm/openai.py
mcpconn-0.1.3.dist-info/METADATA
mcpconn-0.1.3.dist-info/WHEEL
mcpconn-0.1.3.dist-info/licenses/LICENSE
mcpconn-0.1.3.dist-info/RECORD
