Metadata-Version: 2.4
Name: mcpconn
Version: 0.1.3
Summary: Simplified MCP client wrapper for efficient server interactions
Project-URL: Homepage, https://github.com/2796gaurav/mcpconn
Project-URL: Repository, https://github.com/2796gaurav/mcpconn
Author-email: Gaurav Chauhan <2796gaurav@gmail.com>
License-Expression: MIT
License-File: LICENSE
Classifier: Development Status :: 3 - Alpha
Classifier: Intended Audience :: Developers
Classifier: License :: OSI Approved :: MIT License
Classifier: Programming Language :: Python :: 3
Classifier: Programming Language :: Python :: 3.9
Classifier: Programming Language :: Python :: 3.10
Classifier: Programming Language :: Python :: 3.11
Classifier: Programming Language :: Python :: 3.12
Requires-Python: >=3.9
Requires-Dist: anthropic>=0.34.0
Requires-Dist: httpx>=0.25.0
Requires-Dist: mcp>=1.2.0
Requires-Dist: openai>=1.0.0
Requires-Dist: python-dotenv>=1.0.0
Provides-Extra: dev
Requires-Dist: black>=23.0.0; extra == 'dev'
Requires-Dist: mkdocs-material>=9.0.0; extra == 'dev'
Requires-Dist: mkdocs>=1.5.0; extra == 'dev'
Requires-Dist: mypy>=1.0.0; extra == 'dev'
Requires-Dist: pytest>=7.0.0; extra == 'dev'
